generalcartesianproduct/__init__.py
generalcartesianproduct/general_cartesian_product.py
generalcartesianproduct/tests/__init__.py
generalcartesianproduct/tests/test_sage.py
generalcartesianproduct/tests/test_sympy.py
GeneralCartesianProduct-0.1.1.dist-info/LICENSE.txt
GeneralCartesianProduct-0.1.1.dist-info/METADATA
GeneralCartesianProduct-0.1.1.dist-info/WHEEL
GeneralCartesianProduct-0.1.1.dist-info/top_level.txt
GeneralCartesianProduct-0.1.1.dist-info/RECORD
