Metadata-Version: 2.1
Name: GeneralCartesianProduct
Version: 0.1.1
Summary: extends the existing functionality of `itertools.product` by variable limits.
Home-page: https://github.com/FloydZ/generalcartesianproduct
Author: Floyd Z
Author-email: floyd.zweydinger+github@rub.de
License: LICENSE.txt
Platform: UNKNOWN
Classifier: Programming Language :: Python :: 3
Classifier: License :: OSI Approved :: GNU General Public License v2 (GPLv2)
Classifier: Operating System :: OS Independent
Requires-Python: >=3.6
